ektools/__init__.py
ektools/actions.py
ektools/annotations.py
ektools/conversion.py
ektools/date_conversion.py
ektools/korona_parsers.py
ektools/rawdecode.py
ektools/simrad_parsers.py
ektools-0.1.2.data/scripts/eklist
ektools-0.1.2.data/scripts/ekmeta
ektools-0.1.2.data/scripts/ekplot
ektools-0.1.2.data/scripts/eksplit
ektools-0.1.2.dist-info/METADATA
ektools-0.1.2.dist-info/WHEEL
ektools-0.1.2.dist-info/top_level.txt
ektools-0.1.2.dist-info/RECORD
