Metadata-Version: 2.4
Name: ektools
Version: 0.1.2
Summary: Utilities to read and process Simrad RAW files.
Home-page: http://github.com/ketil-malde/ektools
Author: Ketil Malde
Author-email: ketil@malde.org
License: MIT
Classifier: Programming Language :: Python :: 3
Classifier: Development Status :: 4 - Beta
Classifier: Environment :: Console
Requires-Dist: pynmea2
Requires-Dist: numpy
Requires-Dist: lxml
Requires-Dist: pytz
